toolsos/__init__.py
toolsos/cbs_tools.py
toolsos/create_tables.py
toolsos/download.py
toolsos/geo.py
toolsos/helpers.py
toolsos/polars_helpers.py
toolsos/database/database_connection.py
toolsos/database/database_transfer.py
toolsos/huisstijl/__init__.py
toolsos/huisstijl/colors.py
toolsos/huisstijl/graphs/__init__.py
toolsos/huisstijl/graphs/bargraph.py
toolsos/huisstijl/graphs/graph_styles.py
toolsos/huisstijl/graphs/linegraph.py
toolsos/huisstijl/graphs/piegraph.py
toolsos/huisstijl/graphs/styler.py
toolsos/huisstijl/maps/__init__.py
toolsos/huisstijl/maps/choropleth.py
toolsos/huisstijl/tables/__init__.py
toolsos/huisstijl/tables/table_helpers.py
toolsos/huisstijl/tables/table_styles.py
toolsos/huisstijl/tables/tables.py
toolsos-0.3.3.dist-info/METADATA
toolsos-0.3.3.dist-info/WHEEL
toolsos-0.3.3.dist-info/top_level.txt
toolsos-0.3.3.dist-info/RECORD
