Metadata-Version: 2.4
Name: toolsos
Version: 0.3.3
Summary: OS tools
Author-email: OS <d.schmitz@amsterdam.nl>
Keywords: tools,Onderzoek & Statistiek
Classifier: License :: OSI Approved :: MIT License
Classifier: Programming Language :: Python
Classifier: Programming Language :: Python :: 3
Requires-Python: >=3.10
Provides-Extra: dev
Requires-Dist: black; extra == "dev"
Requires-Dist: bumpver; extra == "dev"
Requires-Dist: isort; extra == "dev"
Requires-Dist: pip-tools; extra == "dev"
Requires-Dist: pytest; extra == "dev"
Provides-Extra: all
Requires-Dist: keyring; extra == "all"
Requires-Dist: openpyxl; extra == "all"
Requires-Dist: pandas; extra == "all"
Requires-Dist: plotly; extra == "all"
Requires-Dist: polars; extra == "all"
Requires-Dist: pyarrow; extra == "all"
Requires-Dist: pyreadstat; extra == "all"
Requires-Dist: pyyaml; extra == "all"
Requires-Dist: requests; extra == "all"
Requires-Dist: sqlalchemy; extra == "all"
Requires-Dist: geopandas; extra == "all"
Requires-Dist: ipykernel; extra == "all"
